{
 "id":"Root",
 "layoutOptions":{
  "algorithm":"layered"
 },
 "children":[
  {
   "id":"",
   "width":60,
   "height":60,
   "properties":{
    "portConstraints":"FIXED_ORDER",
    "nodeLabels.placement":"[H_CENTER, V_CENTER, INSIDE]"
   },
   "labels":[
    {
     "text":"P",
     "id":"_label",
     "width":20,
     "height":20
    }
   ],
   "ports":[
    {
     "id":"WEST0",
     "resource":"Res (Machine 0)",
     "properties":{
      "port.side":"WEST",
      "port.index":1
     },
     "width":10,
     "height":10
    },
    {
     "id":"WEST1",
     "resource":"Res (Cash 10)",
     "properties":{
      "port.side":"WEST",
      "port.index":0
     },
     "width":10,
     "height":10
    },
    {
     "id":"EAST0",
     "resource":"Res (Machine 10)",
     "properties":{
      "port.side":"EAST",
      "port.index":0
     },
     "width":10,
     "height":10
    }
   ]
  },
  {
   "id":"OverallWEST0",
   "resource":"Res (Machine 0)",
   "properties":{
    "port.side":"WEST",
    "port.index":1
   },
   "width":10,
   "height":10
  },
  {
   "id":"OverallWEST1",
   "resource":"Res (Cash 10)",
   "properties":{
    "port.side":"WEST",
    "port.index":0
   },
   "width":10,
   "height":10
  },
  {
   "id":"OverallEAST0",
   "resource":"Res (Machine 10)",
   "properties":{
    "port.side":"EAST",
    "port.index":0
   },
   "width":10,
   "height":10
  }
 ],
 "edges":[
  {
   "id":"OverallWEST0-WEST0",
   "sources":[
    "OverallWEST0"
   ],
   "targets":[
    "WEST0"
   ]
  },
  {
   "id":"OverallWEST1-WEST1",
   "sources":[
    "OverallWEST1"
   ],
   "targets":[
    "WEST1"
   ]
  },
  {
   "id":"EAST0-OverallEAST0",
   "sources":[
    "EAST0"
   ],
   "targets":[
    "OverallEAST0"
   ]
  }
 ]
}
